LICENSE
README.md
pyproject.toml
seminar_message_manager/__init__.py
seminar_message_manager/discord_utils.py
seminar_message_manager/mail_utils.py
seminar_message_manager/mattermost_utils.py
seminar_message_manager/parse_template.py
seminar_message_manager/smm.py
seminar_message_manager/zulip_utils.py
seminar_message_manager.egg-info/PKG-INFO
seminar_message_manager.egg-info/SOURCES.txt
seminar_message_manager.egg-info/dependency_links.txt
seminar_message_manager.egg-info/entry_points.txt
seminar_message_manager.egg-info/requires.txt
seminar_message_manager.egg-info/top_level.txt